voltaire/Dockerfile.verify
voltaire/__init__.py
voltaire/_version.py
voltaire/docker-compose.verify.yml
voltaire/graphviz.py
voltaire/mermaid.json
voltaire/mermaid.py
voltaire/pelican.py
voltaire/search.py
voltaire/stats.py
voltaire/tasks.py
voltaire/wikilinks.py
voltaire/theme/static/css/awsm.css
voltaire/theme/static/css/common.scss
voltaire/theme/templates/archives.html
voltaire/theme/templates/article.html
voltaire/theme/templates/author.html
voltaire/theme/templates/authors.html
voltaire/theme/templates/base.html
voltaire/theme/templates/categories.html
voltaire/theme/templates/category.html
voltaire/theme/templates/gosquared.html
voltaire/theme/templates/index.html
voltaire/theme/templates/page.html
voltaire/theme/templates/pagination.html
voltaire/theme/templates/period_archives.html
voltaire/theme/templates/search.html
voltaire/theme/templates/tag.html
voltaire/theme/templates/tags.html
voltaire/theme/templates/translations.html
voltaire-0.17.5.dist-info/LICENSE
voltaire-0.17.5.dist-info/METADATA
voltaire-0.17.5.dist-info/WHEEL
voltaire-0.17.5.dist-info/top_level.txt
voltaire-0.17.5.dist-info/RECORD
