Metadata-Version: 2.1
Name: voltaire
Version: 0.17.5
Summary: Tools for prolific writers (or more accurately, those that want to be).
Home-page: https://github.com/avengerpenguin/voltaire
Author: Ross Fenning
Author-email: github@rossfenning.co.uk
Project-URL: Issue Tracker, https://github.com/avengerpenguin/voltaire/issues
Keywords: pelican,invoke
Classifier: License :: OSI Approved :: GNU General Public License v3 (GPLv3)
Classifier: Development Status :: 5 - Production/Stable
Classifier: Intended Audience :: Developers
Classifier: Operating System :: Unix
Classifier: Operating System :: POSIX
Classifier: Programming Language :: Python
Classifier: Programming Language :: Python :: 3
Classifier: Programming Language :: Python :: 3.5
Classifier: Programming Language :: Python :: 3.6
Classifier: Programming Language :: Python :: 3.7
Classifier: Programming Language :: Python :: 3.8
Classifier: Programming Language :: Python :: Implementation :: CPython
Classifier: Topic :: Internet :: WWW/HTTP
License-File: LICENSE
Requires-Dist: invoke
Requires-Dist: pelican
Requires-Dist: markdown
Requires-Dist: graphviz
Requires-Dist: pelican-webassets
Requires-Dist: pelican-sitemap
Requires-Dist: plantuml-markdown
Requires-Dist: cssmin
Requires-Dist: livereload
Requires-Dist: ghp-import
Requires-Dist: beautifulsoup4
Requires-Dist: typogrify
Requires-Dist: webassets
Requires-Dist: sh
Requires-Dist: doctrine
Provides-Extra: test
Requires-Dist: pytest ; extra == 'test'
Requires-Dist: pytest-shell ; extra == 'test'
Requires-Dist: pytest-shell-utilities ; extra == 'test'
Requires-Dist: pytest-pikachu ; extra == 'test'
Requires-Dist: pytest-mypy ; extra == 'test'
Requires-Dist: xmldiff ; extra == 'test'
Requires-Dist: types-markdown ; extra == 'test'
